coreferee/__init__.py
coreferee/__main__.py
coreferee/annotation.py
coreferee/data_model.py
coreferee/errors.py
coreferee/manager.py
coreferee/rules.py
coreferee/tendencies.py
coreferee/test_utils.py
coreferee/lang/__init__.py
coreferee/lang/common/__init__.py
coreferee/lang/common/data/LICENSE
coreferee/lang/common/data/__init__.py
coreferee/lang/common/data/female_names.dat
coreferee/lang/common/data/male_names.dat
coreferee/lang/de/__init__.py
coreferee/lang/de/config.cfg
coreferee/lang/de/language_specific_rules.py
coreferee/lang/de/data/LICENSE
coreferee/lang/de/data/__init__.py
coreferee/lang/de/data/avalent_verb_stems.dat
coreferee/lang/de/data/blacklisted_phrases.dat
coreferee/lang/de/data/neuter_female_words.dat
coreferee/lang/de/data/neuter_male_words.dat
coreferee/lang/de/data/neuter_person_words.dat
coreferee/lang/de/data/verbs_with_personal_subject.dat
coreferee/lang/en/__init__.py
coreferee/lang/en/config.cfg
coreferee/lang/en/language_specific_rules.py
coreferee/lang/en/data/LICENSE
coreferee/lang/en/data/__init__.py
coreferee/lang/en/data/animal_words.dat
coreferee/lang/en/data/avalent_verbs.dat
coreferee/lang/en/data/blacklisted_phrases.dat
coreferee/lang/en/data/exclusively_female_words.dat
coreferee/lang/en/data/exclusively_male_words.dat
coreferee/lang/en/data/exclusively_person_words.dat
coreferee/lang/en/data/person_words.dat
coreferee/lang/fr/__init__.py
coreferee/lang/fr/config.cfg
coreferee/lang/fr/language_specific_rules.py
coreferee/lang/fr/data/LICENSE
coreferee/lang/fr/data/__init__.py
coreferee/lang/fr/data/animal_words.dat
coreferee/lang/fr/data/avalent_verbs.dat
coreferee/lang/fr/data/blacklisted_nouns.dat
coreferee/lang/fr/data/blacklisted_phrases.dat
coreferee/lang/fr/data/mixed_gender_person_roles.dat
coreferee/lang/fr/data/person_roles.dat
coreferee/lang/fr/data/plural_toponyms.dat
coreferee/lang/fr/data/verbs_with_personal_subject.dat
coreferee/lang/pl/__init__.py
coreferee/lang/pl/config.cfg
coreferee-1.4.1.dist-info/LICENSE
coreferee-1.4.1.dist-info/METADATA
coreferee-1.4.1.dist-info/WHEEL
coreferee-1.4.1.dist-info/entry_points.txt
coreferee-1.4.1.dist-info/top_level.txt
coreferee-1.4.1.dist-info/RECORD
