Metadata-Version: 2.1
Name: coreferee
Version: 1.4.1
Summary: Coreference resolution for English, French, German and Polish, optimised for limited training data and easily extensible for further languages
Home-page: https://github.com/richardpaulhudson/coreferee
Author: Richard Paul Hudson
Author-email: hudsonrichardpaul@gmail.com
License: MIT
Keywords: nlp,spacy,spacy-extension,python,machine-learning,coreference,anaphora,coreference-resolution,anaphora-resolution
Classifier: Development Status :: 5 - Production/Stable
Classifier: Intended Audience :: Developers
Classifier: Intended Audience :: Other Audience
Classifier: Intended Audience :: Education
Classifier: Intended Audience :: Information Technology
Classifier: Intended Audience :: Science/Research
Classifier: License :: OSI Approved :: MIT License
Classifier: Natural Language :: English
Classifier: Natural Language :: French
Classifier: Natural Language :: German
Classifier: Natural Language :: Polish
Classifier: Programming Language :: Python :: 3
Classifier: Programming Language :: Python :: 3.6
Classifier: Programming Language :: Python :: 3.7
Classifier: Programming Language :: Python :: 3.8
Classifier: Programming Language :: Python :: 3.9
Classifier: Programming Language :: Python :: 3.10
Classifier: Programming Language :: Python :: 3.11
Classifier: Topic :: Scientific/Engineering :: Artificial Intelligence
Classifier: Topic :: Text Processing :: Linguistic
Requires-Python: <3.12,>=3.6
License-File: LICENSE
Requires-Dist: spacy (<3.6.0,>=3.0.0)
